jsonvv/__init__.py
jsonvv/__main__.py
jsonvv/exceptions.py
jsonvv/parser.py
jsonvv/strings.py
jsonvv/types.py
jsonvv/validator.py
jsonvv-0.2.2.dist-info/METADATA
jsonvv-0.2.2.dist-info/WHEEL
jsonvv-0.2.2.dist-info/entry_points.txt
jsonvv-0.2.2.dist-info/RECORD
