Metadata-Version: 2.1
Name: jsonvv
Version: 0.2.2
Summary: JSON value validator
Home-page: https://github.com/daijro/camoufox/tree/main/pythonlib/jsonvv
License: MIT
Keywords: json,validator,validation,typing
Author: daijro
Author-email: daijro.dev@gmail.com
Requires-Python: >=3.8,<4.0
Classifier: License :: OSI Approved :: MIT License
Classifier: Programming Language :: Python :: 3
Classifier: Programming Language :: Python :: 3.8
Classifier: Programming Language :: Python :: 3.9
Classifier: Programming Language :: Python :: 3.10
Classifier: Programming Language :: Python :: 3.11
Classifier: Programming Language :: Python :: 3.12
Classifier: Programming Language :: Python :: 3.13
Project-URL: Repository, https://github.com/daijro/camoufox
